pelican_mboxreader/__init__.py
pelican_mboxreader/mboxreader.py
pelican_mboxreader-0.1.4.dist-info/LICENSE
pelican_mboxreader-0.1.4.dist-info/METADATA
pelican_mboxreader-0.1.4.dist-info/WHEEL
pelican_mboxreader-0.1.4.dist-info/top_level.txt
pelican_mboxreader-0.1.4.dist-info/RECORD
