Metadata-Version: 2.1
Name: pelican-mboxreader
Version: 0.1.4
Summary: Pelican plugin that can load articles via email (mailbox / maildir)
Home-page: https://github.com/TC01/pelican-mboxreader/
Author: Ben Rosser
Author-email: rosser.bjr@gmail.com
License: MIT
Keywords: mbox mail pelican markdown blog
Platform: UNKNOWN
Classifier: Development Status :: 4 - Beta
Classifier: Intended Audience :: Developers
Classifier: Topic :: Software Development :: Build Tools
Classifier: License :: OSI Approved :: MIT License
Classifier: Programming Language :: Python :: 2
Classifier: Programming Language :: Python :: 2.6
Classifier: Programming Language :: Python :: 2.7
Classifier: Programming Language :: Python :: 3
Classifier: Programming Language :: Python :: 3.2
Classifier: Programming Language :: Python :: 3.3
Classifier: Programming Language :: Python :: 3.4
Classifier: Programming Language :: Python :: 3.5
Classifier: Programming Language :: Python :: 3.6
Classifier: Topic :: Communications :: Email
Classifier: Topic :: Internet :: WWW/HTTP
Classifier: Topic :: Text Processing
Requires-Dist: pelican
Requires-Dist: python-dateutil
